MANIFEST.in
README.md
requirements.txt
setup.py
rqopen_client/__init__.py
rqopen_client/client.py
rqopen_client.egg-info/PKG-INFO
rqopen_client.egg-info/SOURCES.txt
rqopen_client.egg-info/dependency_links.txt
rqopen_client.egg-info/not-zip-safe
rqopen_client.egg-info/requires.txt
rqopen_client.egg-info/top_level.txt