Metadata-Version: 1.0
Name: rqopen-client
Version: 0.0.4
Summary: rqopen-client
Home-page: https://github.com/ricequant/rqopen-client
Author: ricequant
Author-email: public@ricequant.com
License: UNKNOWN
Platform: UNKNOWN
